dirt/__init__.py
dirt/builder.py
dirt/checker.py
dirt/common.py
dirt/composer.py
dirt/config.py
dirt/conversion.py
dirt/dirtcontext.py
dirt/extras.py
dirt/feeds.py
dirt/fx_pico.py
dirt/fx_tufte.py
dirt/gdocs.py
dirt/generate.py
dirt/htmlify.py
dirt/localserver.py
dirt/main.py
dirt/meta/_config.toml
dirt/meta/dirt.toml
dirt/meta/frameworks/pico/style/pico.min.css
dirt/meta/frameworks/tufte/style/tufte.css
dirt/meta/index.md
dirt/meta/local_jscript.html
dirt/meta/pico_template.html
dirt/meta/rss_feed_template.xml
dirt/meta/rss_item_template.xml
dirt/meta/tufte_template.html
dirt/pageinfo.py
dirt/ssg.py
dirt/urls.py
dirt/words.py
dirt_ssg-0.2.0.dist-info/METADATA
dirt_ssg-0.2.0.dist-info/WHEEL
dirt_ssg-0.2.0.dist-info/entry_points.txt
dirt_ssg-0.2.0.dist-info/RECORD
