Metadata-Version: 2.1
Name: dirt-ssg
Version: 0.2.0
Summary: 
Author: Loren Kohnfelder
Requires-Python: >=3.10,<4.0
Classifier: Programming Language :: Python :: 3
Classifier: Programming Language :: Python :: 3.10
Classifier: Programming Language :: Python :: 3.11
Requires-Dist: Markdown (>=3.3.7,<4.0.0)
Requires-Dist: toml (>=0.10.2,<0.11.0)
Requires-Dist: watchdog (>=2.1.8,<3.0.0)
